[{"model": "products.product", "pk": 1, "fields": {"name": "Men's Shirt", "description": "", "image": "product_images/p1.png", "price": "75.00", "quantity": 10, "category": 1}}, {"model": "products.product", "pk": 2, "fields": {"name": "Boy's Shirt", "description": "", "image": "product_images/p2.png", "price": "80.00", "quantity": 10, "category": 3}}, {"model": "products.product", "pk": 3, "fields": {"name": "Women's Dress", "description": "", "image": "product_images/p3.png", "price": "70.00", "quantity": 10, "category": 2}}, {"model": "products.product", "pk": 4, "fields": {"name": "Girl's Dress", "description": "", "image": "product_images/p4.png", "price": "50.00", "quantity": 10, "category": 4}}]